{"cameraMode":{"drawMode":0,"name":"Shaded","section":"Shading Mode"},"sceneLighting":true,"audioPlay":false,"sceneViewState":{"m_AlwaysRefresh":false,"showFog":true,"showSkybox":true,"showFlares":true,"showImageEffects":true,"showParticleSystems":true,"showVisualEffectGraphs":true,"m_FxEnabled":true},"in2DMode":false,"pivot":{"x":3.1799802780151369,"y":1.2221400737762452,"z":-0.6007382273674011},"rotation":{"x":-0.23220239579677583,"y":-0.4879296123981476,"z":0.13650207221508027,"w":-0.8303357362747192},"size":3.6779227256774904,"orthographic":false}